{
	"name": "Dataflow_Summary",
	"properties": {
		"type": "MappingDataFlow",
		"typeProperties": {
			"sources": [
				{
					"dataset": {
						"referenceName": "ds_sql_nyc_payroll_data_2020",
						"type": "DatasetReference"
					},
					"name": "SourcePayroll2020"
				},
				{
					"dataset": {
						"referenceName": "ds_sql_nyc_payroll_data_2021",
						"type": "DatasetReference"
					},
					"name": "SourcePayroll2021"
				}
			],
			"sinks": [],
			"transformations": [
				{
					"name": "UnionPayrollData"
				},
				{
					"name": "SelectPayroll2020"
				},
				{
					"name": "SelectPayroll2021"
				},
				{
					"name": "FilterFiscalYear"
				}
			],
			"scriptLines": [
				"source(output(",
				"          FiscalYear as integer,",
				"          PayrollNumber as integer,",
				"          AgencyID as string,",
				"          AgencyName as string,",
				"          EmployeeID as string,",
				"          LastName as string,",
				"          FirstName as string,",
				"          AgencyStartDate as date,",
				"          WorkLocationBorough as string,",
				"          TitleCode as string,",
				"          TitleDescription as string,",
				"          LeaveStatusasofJune30 as string,",
				"          BaseSalary as double,",
				"          PayBasis as string,",
				"          RegularHours as double,",
				"          RegularGrossPaid as double,",
				"          OTHours as double,",
				"          TotalOTPaid as double,",
				"          TotalOtherPay as double",
				"     ),",
				"     allowSchemaDrift: true,",
				"     validateSchema: false,",
				"     isolationLevel: 'READ_UNCOMMITTED',",
				"     format: 'table') ~> SourcePayroll2020",
				"source(output(",
				"          FiscalYear as integer,",
				"          PayrollNumber as integer,",
				"          AgencyCode as string,",
				"          AgencyName as string,",
				"          EmployeeID as string,",
				"          LastName as string,",
				"          FirstName as string,",
				"          AgencyStartDate as date,",
				"          WorkLocationBorough as string,",
				"          TitleCode as string,",
				"          TitleDescription as string,",
				"          LeaveStatusasofJune30 as string,",
				"          BaseSalary as double,",
				"          PayBasis as string,",
				"          RegularHours as double,",
				"          RegularGrossPaid as double,",
				"          OTHours as double,",
				"          TotalOTPaid as double,",
				"          TotalOtherPay as double",
				"     ),",
				"     allowSchemaDrift: true,",
				"     validateSchema: false,",
				"     isolationLevel: 'READ_UNCOMMITTED',",
				"     format: 'table') ~> SourcePayroll2021",
				"SelectPayroll2020, SourcePayroll2021 union(byName: true)~> UnionPayrollData",
				"SourcePayroll2020 select(mapColumn(",
				"          FiscalYear,",
				"          PayrollNumber,",
				"          AgencyID,",
				"          AgencyName,",
				"          EmployeeID,",
				"          LastName,",
				"          FirstName,",
				"          AgencyStartDate,",
				"          WorkLocationBorough,",
				"          TitleCode,",
				"          TitleDescription,",
				"          LeaveStatusasofJune30,",
				"          BaseSalary,",
				"          PayBasis,",
				"          RegularHours,",
				"          RegularGrossPaid,",
				"          OTHours,",
				"          TotalOTPaid,",
				"          TotalOtherPay",
				"     ),",
				"     skipDuplicateMapInputs: true,",
				"     skipDuplicateMapOutputs: true) ~> SelectPayroll2020",
				"SourcePayroll2021 select(mapColumn(",
				"          FiscalYear,",
				"          PayrollNumber,",
				"          AgencyCode,",
				"          AgencyName,",
				"          EmployeeID,",
				"          LastName,",
				"          FirstName,",
				"          AgencyStartDate,",
				"          WorkLocationBorough,",
				"          TitleCode,",
				"          TitleDescription,",
				"          LeaveStatusasofJune30,",
				"          BaseSalary,",
				"          PayBasis,",
				"          RegularHours,",
				"          RegularGrossPaid,",
				"          OTHours,",
				"          TotalOTPaid,",
				"          TotalOtherPay",
				"     ),",
				"     skipDuplicateMapInputs: true,",
				"     skipDuplicateMapOutputs: true) ~> SelectPayroll2021",
				"UnionPayrollData filter(ERROR_FUNCTION('')) ~> FilterFiscalYear"
			]
		}
	}
}