{
	"$schema": "http://schema.management.azure.com/schemas/2015-01-01/deploymentTemplate.json#",
	"contentVersion": "1.0.0.0",
	"parameters": {
		"factoryName": {
			"type": "string",
			"metadata": "Data Factory name",
			"defaultValue": "ADF-NYC-Payroll"
		}
	},
	"variables": {
		"factoryId": "[concat('Microsoft.DataFactory/factories/', parameters('factoryName'))]"
	},
	"resources": [
		{
			"name": "[concat(parameters('factoryName'), '/Pipeline_Creation')]",
			"type": "Microsoft.DataFactory/factories/pipelines",
			"apiVersion": "2018-06-01",
			"properties": {
				"activities": [
					{
						"name": "dataflow_agency",
						"type": "ExecuteDataFlow",
						"dependsOn": [],
						"policy": {
							"timeout": "0.12:00:00",
							"retry": 0,
							"retryIntervalInSeconds": 30,
							"secureOutput": false,
							"secureInput": false
						},
						"userProperties": [],
						"typeProperties": {
							"dataflow": {
								"referenceName": "Load_Agency_Master_Data",
								"type": "DataFlowReference",
								"parameters": {},
								"datasetParameters": {
									"SourceAgencyMaster": {},
									"SinkAgencyMaster": {}
								}
							},
							"staging": {},
							"compute": {
								"coreCount": 8,
								"computeType": "General"
							},
							"traceLevel": "Fine"
						}
					},
					{
						"name": "dataflow_emp",
						"type": "ExecuteDataFlow",
						"dependsOn": [],
						"policy": {
							"timeout": "0.12:00:00",
							"retry": 0,
							"retryIntervalInSeconds": 30,
							"secureOutput": false,
							"secureInput": false
						},
						"userProperties": [],
						"typeProperties": {
							"dataflow": {
								"referenceName": "Load_Employee_Master_Data",
								"type": "DataFlowReference",
								"parameters": {},
								"datasetParameters": {
									"SourceEmpMaster": {},
									"SinkEmpMaster": {}
								}
							},
							"staging": {},
							"compute": {
								"coreCount": 8,
								"computeType": "General"
							},
							"traceLevel": "Fine"
						}
					},
					{
						"name": "dataflow_title",
						"type": "ExecuteDataFlow",
						"dependsOn": [],
						"policy": {
							"timeout": "0.12:00:00",
							"retry": 0,
							"retryIntervalInSeconds": 30,
							"secureOutput": false,
							"secureInput": false
						},
						"userProperties": [],
						"typeProperties": {
							"dataflow": {
								"referenceName": "Load_Job_Title_Data",
								"type": "DataFlowReference",
								"parameters": {},
								"datasetParameters": {
									"SourceTitleMaster": {},
									"SinkTitleMaster": {}
								}
							},
							"staging": {},
							"compute": {
								"coreCount": 8,
								"computeType": "General"
							},
							"traceLevel": "Fine"
						}
					},
					{
						"name": "Load_2021_Payroll_Data",
						"type": "ExecuteDataFlow",
						"dependsOn": [
							{
								"activity": "dataflow_agency",
								"dependencyConditions": [
									"Succeeded"
								]
							},
							{
								"activity": "dataflow_emp",
								"dependencyConditions": [
									"Succeeded"
								]
							},
							{
								"activity": "dataflow_title",
								"dependencyConditions": [
									"Succeeded"
								]
							}
						],
						"policy": {
							"timeout": "0.12:00:00",
							"retry": 0,
							"retryIntervalInSeconds": 30,
							"secureOutput": false,
							"secureInput": false
						},
						"userProperties": [],
						"typeProperties": {
							"dataflow": {
								"referenceName": "Load_2021_Payroll_Data",
								"type": "DataFlowReference",
								"parameters": {},
								"datasetParameters": {
									"Source2021Payroll": {},
									"Sink2021Payroll": {}
								}
							},
							"staging": {},
							"compute": {
								"coreCount": 8,
								"computeType": "General"
							},
							"traceLevel": "Fine"
						}
					},
					{
						"name": "Load_2020_Payroll_Data",
						"type": "ExecuteDataFlow",
						"dependsOn": [
							{
								"activity": "dataflow_agency",
								"dependencyConditions": [
									"Succeeded"
								]
							},
							{
								"activity": "dataflow_emp",
								"dependencyConditions": [
									"Succeeded"
								]
							},
							{
								"activity": "dataflow_title",
								"dependencyConditions": [
									"Succeeded"
								]
							}
						],
						"policy": {
							"timeout": "0.12:00:00",
							"retry": 0,
							"retryIntervalInSeconds": 30,
							"secureOutput": false,
							"secureInput": false
						},
						"userProperties": [],
						"typeProperties": {
							"dataflow": {
								"referenceName": "Load_2020_Payroll_Data",
								"type": "DataFlowReference",
								"parameters": {},
								"datasetParameters": {
									"Source2020Payroll": {},
									"Sink2020Payroll": {}
								}
							},
							"staging": {},
							"compute": {
								"coreCount": 8,
								"computeType": "General"
							},
							"traceLevel": "Fine"
						}
					},
					{
						"name": "Dataflow_Summary",
						"type": "ExecuteDataFlow",
						"dependsOn": [
							{
								"activity": "Load_2020_Payroll_Data",
								"dependencyConditions": [
									"Succeeded"
								]
							},
							{
								"activity": "Load_2021_Payroll_Data",
								"dependencyConditions": [
									"Succeeded"
								]
							}
						],
						"policy": {
							"timeout": "0.12:00:00",
							"retry": 0,
							"retryIntervalInSeconds": 30,
							"secureOutput": false,
							"secureInput": false
						},
						"userProperties": [],
						"typeProperties": {
							"dataflow": {
								"referenceName": "Dataflow_Summary",
								"type": "DataFlowReference",
								"parameters": {
									"dataflow_param_fiscalyear": "2020"
								},
								"datasetParameters": {
									"SourcePayroll2020": {},
									"SourcePayroll2021": {},
									"SQLSink": {},
									"DataLakeSink": {}
								}
							},
							"staging": {},
							"compute": {
								"coreCount": 8,
								"computeType": "General"
							},
							"traceLevel": "Fine"
						}
					}
				],
				"policy": {
					"elapsedTimeMetric": {}
				},
				"annotations": []
			},
			"dependsOn": []
		},
		{
			"name": "[concat(parameters('factoryName'), '/pipeline2')]",
			"type": "Microsoft.DataFactory/factories/pipelines",
			"apiVersion": "2018-06-01",
			"properties": {
				"activities": [
					{
						"name": "dataflow_agency",
						"type": "ExecuteDataFlow",
						"dependsOn": [],
						"policy": {
							"timeout": "0.12:00:00",
							"retry": 0,
							"retryIntervalInSeconds": 30,
							"secureOutput": false,
							"secureInput": false
						},
						"userProperties": [],
						"typeProperties": {
							"dataflow": {
								"referenceName": "Load_Agency_Master_Data",
								"type": "DataFlowReference",
								"parameters": {},
								"datasetParameters": {
									"SourceAgencyMaster": {},
									"SinkAgencyMaster": {}
								}
							},
							"staging": {},
							"compute": {
								"coreCount": 8,
								"computeType": "General"
							},
							"traceLevel": "Fine"
						}
					},
					{
						"name": "dataflow_emp",
						"type": "ExecuteDataFlow",
						"dependsOn": [],
						"policy": {
							"timeout": "0.12:00:00",
							"retry": 0,
							"retryIntervalInSeconds": 30,
							"secureOutput": false,
							"secureInput": false
						},
						"userProperties": [],
						"typeProperties": {
							"dataflow": {
								"referenceName": "Load_Employee_Master_Data",
								"type": "DataFlowReference",
								"parameters": {},
								"datasetParameters": {
									"SourceEmpMaster": {},
									"SinkEmpMaster": {}
								}
							},
							"staging": {},
							"compute": {
								"coreCount": 8,
								"computeType": "General"
							},
							"traceLevel": "Fine"
						}
					},
					{
						"name": "dataflow_title",
						"type": "ExecuteDataFlow",
						"dependsOn": [],
						"policy": {
							"timeout": "0.12:00:00",
							"retry": 0,
							"retryIntervalInSeconds": 30,
							"secureOutput": false,
							"secureInput": false
						},
						"userProperties": [],
						"typeProperties": {
							"dataflow": {
								"referenceName": "Load_Job_Title_Data",
								"type": "DataFlowReference",
								"parameters": {},
								"datasetParameters": {
									"SourceTitleMaster": {},
									"SinkTitleMaster": {}
								}
							},
							"staging": {},
							"compute": {
								"coreCount": 8,
								"computeType": "General"
							},
							"traceLevel": "Fine"
						}
					},
					{
						"name": "Load_2021_Payroll_Data",
						"type": "ExecuteDataFlow",
						"dependsOn": [
							{
								"activity": "dataflow_agency",
								"dependencyConditions": [
									"Succeeded"
								]
							},
							{
								"activity": "dataflow_emp",
								"dependencyConditions": [
									"Succeeded"
								]
							},
							{
								"activity": "dataflow_title",
								"dependencyConditions": [
									"Succeeded"
								]
							}
						],
						"policy": {
							"timeout": "0.12:00:00",
							"retry": 0,
							"retryIntervalInSeconds": 30,
							"secureOutput": false,
							"secureInput": false
						},
						"userProperties": [],
						"typeProperties": {
							"dataflow": {
								"referenceName": "Load_2021_Payroll_Data",
								"type": "DataFlowReference",
								"parameters": {},
								"datasetParameters": {
									"Source2021Payroll": {},
									"Sink2021Payroll": {}
								}
							},
							"staging": {},
							"compute": {
								"coreCount": 8,
								"computeType": "General"
							},
							"traceLevel": "Fine"
						}
					},
					{
						"name": "Load_2020_Payroll_Data",
						"type": "ExecuteDataFlow",
						"dependsOn": [
							{
								"activity": "dataflow_agency",
								"dependencyConditions": [
									"Succeeded"
								]
							},
							{
								"activity": "dataflow_emp",
								"dependencyConditions": [
									"Succeeded"
								]
							},
							{
								"activity": "dataflow_title",
								"dependencyConditions": [
									"Succeeded"
								]
							}
						],
						"policy": {
							"timeout": "0.12:00:00",
							"retry": 0,
							"retryIntervalInSeconds": 30,
							"secureOutput": false,
							"secureInput": false
						},
						"userProperties": [],
						"typeProperties": {
							"dataflow": {
								"referenceName": "Load_2020_Payroll_Data",
								"type": "DataFlowReference",
								"parameters": {},
								"datasetParameters": {
									"Source2020Payroll": {},
									"Sink2020Payroll": {}
								}
							},
							"staging": {},
							"compute": {
								"coreCount": 8,
								"computeType": "General"
							},
							"traceLevel": "Fine"
						}
					},
					{
						"name": "Dataflow_Summary",
						"type": "ExecuteDataFlow",
						"dependsOn": [
							{
								"activity": "Load_2021_Payroll_Data",
								"dependencyConditions": [
									"Succeeded"
								]
							},
							{
								"activity": "Load_2020_Payroll_Data",
								"dependencyConditions": [
									"Succeeded"
								]
							}
						],
						"policy": {
							"timeout": "0.12:00:00",
							"retry": 0,
							"retryIntervalInSeconds": 30,
							"secureOutput": false,
							"secureInput": false
						},
						"userProperties": [],
						"typeProperties": {
							"dataflow": {
								"referenceName": "Dataflow_Summary",
								"type": "DataFlowReference",
								"parameters": {
									"dataflow_param_fiscalyear": "2020"
								},
								"datasetParameters": {
									"SourcePayroll2020": {},
									"SourcePayroll2021": {},
									"SQLSink": {},
									"DataLakeSink": {}
								}
							},
							"staging": {},
							"compute": {
								"coreCount": 8,
								"computeType": "General"
							},
							"traceLevel": "Fine"
						}
					}
				],
				"policy": {
					"elapsedTimeMetric": {}
				},
				"annotations": []
			},
			"dependsOn": []
		}
	]
}